[
  {
    "title": "Upwork",
    "tags": ["Vue", "Node.js", "Typescript", "GraphQL"],
    "image": "/images/project-cypher.jpg",
    "links": {
      "live": "https://www.upwork.com/nx/search/jobs",
      "github": "#"
    }
  },
  {
    "title": "Narbox",
    "tags": ["Python", "Next.js", "GraphQL", "Django", "PostgresSQL"],
    "image": "/images/neural-net.jpg",
    "links": {
      "live": "https://www.instagram.com/narboxcourier/?hl=es-la",
      "github": "https://github.com/juanelojga/nbx-django"
    }
  },
  {
    "title": "Personal Page",
    "tags": ["Astro", "Tailwind", "TypeScript"],
    "image": "/images/decentralized-app.jpg",
    "links": {
      "live": "https://juanelojga.com/",
      "github": "https://github.com/juanelojga/juanelojga-webpage"
    }
  }
]
